[
  {
    "description": "    application regression",
    "keyword": "Feature",
    "name": "End to end Ecommerce validation",
    "line": 1,
    "id": "end-to-end-ecommerce-validation",
    "tags": [],
    "uri": "ecommerce.feature",
    "elements": [
      {
        "id": "end-to-end-ecommerce-validation;ecommerce-products-delivery",
        "keyword": "Scenario",
        "line": 5,
        "name": "Ecommerce products delivery",
        "tags": [
          {
            "name": "@Regression",
            "line": 4
          }
        ],
        "type": "scenario",
        "steps": [
          {
            "arguments": [],
            "keyword": "Given ",
            "line": 6,
            "name": "I open Ecommerce page",
            "result": {
              "status": "passed",
              "duration": 1972000000
            }
          },
          {
            "arguments": [],
            "keyword": "When ",
            "line": 7,
            "name": "I add items to cart",
            "result": {
              "status": "passed",
              "duration": 2302000000
            }
          },
          {
            "arguments": [],
            "keyword": "And ",
            "line": 8,
            "name": "Validate the total prices",
            "result": {
              "status": "passed",
              "duration": 40000000
            }
          },
          {
            "arguments": [],
            "keyword": "Then ",
            "line": 9,
            "name": "Select the country, submit and verify Thank you",
            "result": {
              "status": "passed",
              "duration": 5569000000
            }
          }
        ]
      },
      {
        "id": "end-to-end-ecommerce-validation;filling-the-form-to-shop",
        "keyword": "Scenario",
        "line": 12,
        "name": "Filling the form to shop",
        "tags": [
          {
            "name": "@Smoke",
            "line": 11
          }
        ],
        "type": "scenario",
        "steps": [
          {
            "arguments": [],
            "keyword": "Given ",
            "line": 13,
            "name": "I open Ecommerce page",
            "result": {
              "status": "passed",
              "duration": 1035000000
            }
          },
          {
            "arguments": [
              {
                "rows": [
                  {
                    "cells": [
                      "name",
                      "gender",
                      "password",
                      "email",
                      "ifyouLoveIceCreams",
                      "employmentStatus",
                      "date",
                      "ProductName"
                    ]
                  },
                  {
                    "cells": [
                      "Alex",
                      "Male",
                      "qwer12",
                      "alex@test.test",
                      "false",
                      "Student",
                      "2010-06-11",
                      "iphone X"
                    ]
                  },
                  {
                    "cells": [
                      "Greg",
                      "Male",
                      "qwerty1",
                      "greg@test.test",
                      "true",
                      "Student",
                      "2010-04-04",
                      "Nokia Edge"
                    ]
                  }
                ]
              }
            ],
            "keyword": "When ",
            "line": 14,
            "name": "I fill the form details",
            "result": {
              "status": "passed",
              "duration": 1313000000
            }
          },
          {
            "arguments": [],
            "keyword": "Then ",
            "line": 19,
            "name": "Validate the form behavior",
            "result": {
              "status": "passed",
              "duration": 19000000
            }
          },
          {
            "arguments": [],
            "keyword": "And ",
            "line": 20,
            "name": "Select the shop page",
            "result": {
              "status": "passed",
              "duration": 329000000
            }
          }
        ]
      }
    ]
  }
]